{
  "teamId": 71,
  "season": 2019,
  "byTimeAvailable": false,
  "scored": {
    "total": 26,
    "byTime": null
  },
  "conceded": {
    "total": 75,
    "byTime": null
  },
  "home": {
    "scored": {
      "total": null,
      "byTime": null
    },
    "conceded": {
      "total": null,
      "byTime": null
    }
  },
  "away": {
    "scored": {
      "total": null,
      "byTime": null
    },
    "conceded": {
      "total": null,
      "byTime": null
    }
  },
  "recentForm": [
    "L",
    "L",
    "L",
    "L",
    "L"
  ],
  "scorers": [
    {
      "id": 19085,
      "name": "T. Pukki",
      "photo": "https://media.api-sports.io/football/players/19085.png",
      "goals": 11,
      "assists": 3,
      "appearances": 36
    },
    {
      "id": 19072,
      "name": "T. Cantwell",
      "photo": "https://media.api-sports.io/football/players/19072.png",
      "goals": 6,
      "assists": 2,
      "appearances": 37
    },
    {
      "id": 19071,
      "name": "E. Buendía",
      "photo": "https://media.api-sports.io/football/players/19071.png",
      "goals": 1,
      "assists": 7,
      "appearances": 36
    },
    {
      "id": 19077,
      "name": "K. McLean",
      "photo": "https://media.api-sports.io/football/players/19077.png",
      "goals": 1,
      "assists": 1,
      "appearances": 37
    },
    {
      "id": 19079,
      "name": "Alexander Banor Tettey",
      "photo": "https://media.api-sports.io/football/players/19079.png",
      "goals": 1,
      "assists": 1,
      "appearances": 30
    },
    {
      "id": 25643,
      "name": "J. Drmić",
      "photo": "https://media.api-sports.io/football/players/25643.png",
      "goals": 1,
      "assists": 0,
      "appearances": 21
    },
    {
      "id": 19074,
      "name": "O. Hernández",
      "photo": "https://media.api-sports.io/football/players/19074.png",
      "goals": 1,
      "assists": 2,
      "appearances": 26
    },
    {
      "id": 19082,
      "name": "M. Vrančić",
      "photo": "https://media.api-sports.io/football/players/19082.png",
      "goals": 1,
      "assists": 0,
      "appearances": 20
    },
    {
      "id": 19087,
      "name": "D. Srbeny",
      "photo": "https://media.api-sports.io/football/players/19087.png",
      "goals": 1,
      "assists": 0,
      "appearances": 8
    },
    {
      "id": 19076,
      "name": "J. Lewis",
      "photo": "https://media.api-sports.io/football/players/19076.png",
      "goals": 1,
      "assists": 0,
      "appearances": 28
    }
  ],
  "fixtures": [
    {
      "id": 157391,
      "season": 2019,
      "team_id": 71,
      "match_date": "2020-07-26T15:00:00+00:00",
      "home_team_id": 50,
      "away_team_id": 71,
      "home_team_name": "Manchester City",
      "away_team_name": "Norwich",
      "goals_home": 5,
      "goals_away": 0,
      "ht_home": 2,
      "ht_away": 0,
      "status": "FT",
      "stats_home": {
        "shots_on_goal": 10,
        "shots_off_goal": 12,
        "total_shots": 31,
        "blocked_shots": 9,
        "corners": 9,
        "possession": 73,
        "fouls": 7,
        "yellow_cards": 1,
        "red_cards": null,
        "saves": 4,
        "total_passes": 722,
        "pass_accuracy": 92
      },
      "stats_away": {
        "shots_on_goal": 4,
        "shots_off_goal": 1,
        "total_shots": 5,
        "blocked_shots": 0,
        "corners": 0,
        "possession": 27,
        "fouls": 4,
        "yellow_cards": 1,
        "red_cards": null,
        "saves": 4,
        "total_passes": 268,
        "pass_accuracy": 72
      }
    },
    {
      "id": 157380,
      "season": 2019,
      "team_id": 71,
      "match_date": "2020-07-18T16:30:00+00:00",
      "home_team_id": 71,
      "away_team_id": 44,
      "home_team_name": "Norwich",
      "away_team_name": "Burnley",
      "goals_home": 0,
      "goals_away": 2,
      "ht_home": 0,
      "ht_away": 1,
      "status": "FT",
      "stats_home": {
        "shots_on_goal": 2,
        "shots_off_goal": 2,
        "total_shots": 6,
        "blocked_shots": 2,
        "corners": 6,
        "possession": 42,
        "fouls": 9,
        "yellow_cards": null,
        "red_cards": 2,
        "saves": 7,
        "total_passes": 354,
        "pass_accuracy": 75
      },
      "stats_away": {
        "shots_on_goal": 8,
        "shots_off_goal": 7,
        "total_shots": 23,
        "blocked_shots": 8,
        "corners": 8,
        "possession": 58,
        "fouls": 16,
        "yellow_cards": null,
        "red_cards": 0,
        "saves": 2,
        "total_passes": 468,
        "pass_accuracy": 86
      }
    },
    {
      "id": 157367,
      "season": 2019,
      "team_id": 71,
      "match_date": "2020-07-14T19:15:00+00:00",
      "home_team_id": 49,
      "away_team_id": 71,
      "home_team_name": "Chelsea",
      "away_team_name": "Norwich",
      "goals_home": 1,
      "goals_away": 0,
      "ht_home": 1,
      "ht_away": 0,
      "status": "FT",
      "stats_home": {
        "shots_on_goal": 6,
        "shots_off_goal": 12,
        "total_shots": 22,
        "blocked_shots": 4,
        "corners": 8,
        "possession": 67,
        "fouls": 10,
        "yellow_cards": 2,
        "red_cards": null,
        "saves": 0,
        "total_passes": 772,
        "pass_accuracy": 89
      },
      "stats_away": {
        "shots_on_goal": 0,
        "shots_off_goal": 0,
        "total_shots": 2,
        "blocked_shots": 2,
        "corners": 1,
        "possession": 33,
        "fouls": 9,
        "yellow_cards": 2,
        "red_cards": null,
        "saves": 5,
        "total_passes": 374,
        "pass_accuracy": 77
      }
    },
    {
      "id": 157360,
      "season": 2019,
      "team_id": 71,
      "match_date": "2020-07-11T11:30:00+00:00",
      "home_team_id": 71,
      "away_team_id": 48,
      "home_team_name": "Norwich",
      "away_team_name": "West Ham",
      "goals_home": 0,
      "goals_away": 4,
      "ht_home": 0,
      "ht_away": 2,
      "status": "FT",
      "stats_home": {
        "shots_on_goal": 2,
        "shots_off_goal": 6,
        "total_shots": 11,
        "blocked_shots": 3,
        "corners": 1,
        "possession": 52,
        "fouls": 9,
        "yellow_cards": 1,
        "red_cards": null,
        "saves": 3,
        "total_passes": 542,
        "pass_accuracy": 87
      },
      "stats_away": {
        "shots_on_goal": 7,
        "shots_off_goal": 11,
        "total_shots": 19,
        "blocked_shots": 1,
        "corners": 6,
        "possession": 48,
        "fouls": 8,
        "yellow_cards": 0,
        "red_cards": null,
        "saves": 2,
        "total_passes": 478,
        "pass_accuracy": 83
      }
    },
    {
      "id": 157353,
      "season": 2019,
      "team_id": 71,
      "match_date": "2020-07-07T17:00:00+00:00",
      "home_team_id": 38,
      "away_team_id": 71,
      "home_team_name": "Watford",
      "away_team_name": "Norwich",
      "goals_home": 2,
      "goals_away": 1,
      "ht_home": 1,
      "ht_away": 1,
      "status": "FT",
      "stats_home": {
        "shots_on_goal": 4,
        "shots_off_goal": 5,
        "total_shots": 9,
        "blocked_shots": 0,
        "corners": 4,
        "possession": 43,
        "fouls": 11,
        "yellow_cards": 2,
        "red_cards": null,
        "saves": 2,
        "total_passes": 375,
        "pass_accuracy": 73
      },
      "stats_away": {
        "shots_on_goal": 3,
        "shots_off_goal": 6,
        "total_shots": 12,
        "blocked_shots": 3,
        "corners": 3,
        "possession": 57,
        "fouls": 15,
        "yellow_cards": 4,
        "red_cards": null,
        "saves": 2,
        "total_passes": 504,
        "pass_accuracy": 83
      }
    },
    {
      "id": 157341,
      "season": 2019,
      "team_id": 71,
      "match_date": "2020-07-04T11:30:00+00:00",
      "home_team_id": 71,
      "away_team_id": 51,
      "home_team_name": "Norwich",
      "away_team_name": "Brighton",
      "goals_home": 0,
      "goals_away": 1,
      "ht_home": 0,
      "ht_away": 1,
      "status": "FT",
      "stats_home": {
        "shots_on_goal": 1,
        "shots_off_goal": 4,
        "total_shots": 12,
        "blocked_shots": 7,
        "corners": 0,
        "possession": 58,
        "fouls": 11,
        "yellow_cards": 2,
        "red_cards": null,
        "saves": 1,
        "total_passes": 587,
        "pass_accuracy": 86
      },
      "stats_away": {
        "shots_on_goal": 2,
        "shots_off_goal": 3,
        "total_shots": 8,
        "blocked_shots": 3,
        "corners": 2,
        "possession": 42,
        "fouls": 13,
        "yellow_cards": 2,
        "red_cards": null,
        "saves": 1,
        "total_passes": 418,
        "pass_accuracy": 83
      }
    },
    {
      "id": 157326,
      "season": 2019,
      "team_id": 71,
      "match_date": "2020-07-01T17:00:00+00:00",
      "home_team_id": 42,
      "away_team_id": 71,
      "home_team_name": "Arsenal",
      "away_team_name": "Norwich",
      "goals_home": 4,
      "goals_away": 0,
      "ht_home": 2,
      "ht_away": 0,
      "status": "FT",
      "stats_home": {
        "shots_on_goal": 8,
        "shots_off_goal": 4,
        "total_shots": 13,
        "blocked_shots": 1,
        "corners": 6,
        "possession": 51,
        "fouls": 10,
        "yellow_cards": 1,
        "red_cards": null,
        "saves": 2,
        "total_passes": 468,
        "pass_accuracy": 85
      },
      "stats_away": {
        "shots_on_goal": 2,
        "shots_off_goal": 3,
        "total_shots": 8,
        "blocked_shots": 3,
        "corners": 2,
        "possession": 49,
        "fouls": 10,
        "yellow_cards": 4,
        "red_cards": null,
        "saves": 4,
        "total_passes": 445,
        "pass_accuracy": 80
      }
    },
    {
      "id": 157321,
      "season": 2019,
      "team_id": 71,
      "match_date": "2020-06-24T17:00:00+00:00",
      "home_team_id": 71,
      "away_team_id": 45,
      "home_team_name": "Norwich",
      "away_team_name": "Everton",
      "goals_home": 0,
      "goals_away": 1,
      "ht_home": 0,
      "ht_away": 0,
      "status": "FT",
      "stats_home": {
        "shots_on_goal": 1,
        "shots_off_goal": 2,
        "total_shots": 9,
        "blocked_shots": 6,
        "corners": 6,
        "possession": 46,
        "fouls": 8,
        "yellow_cards": 0,
        "red_cards": null,
        "saves": 4,
        "total_passes": 432,
        "pass_accuracy": 80
      },
      "stats_away": {
        "shots_on_goal": 5,
        "shots_off_goal": 3,
        "total_shots": 12,
        "blocked_shots": 4,
        "corners": 5,
        "possession": 54,
        "fouls": 13,
        "yellow_cards": 1,
        "red_cards": null,
        "saves": 1,
        "total_passes": 495,
        "pass_accuracy": 80
      }
    },
    {
      "id": 157311,
      "season": 2019,
      "team_id": 71,
      "match_date": "2020-06-19T17:00:00+00:00",
      "home_team_id": 71,
      "away_team_id": 41,
      "home_team_name": "Norwich",
      "away_team_name": "Southampton",
      "goals_home": 0,
      "goals_away": 3,
      "ht_home": 0,
      "ht_away": 0,
      "status": "FT",
      "stats_home": {
        "shots_on_goal": 1,
        "shots_off_goal": 3,
        "total_shots": 9,
        "blocked_shots": 5,
        "corners": 9,
        "possession": 55,
        "fouls": 9,
        "yellow_cards": 1,
        "red_cards": null,
        "saves": 6,
        "total_passes": 406,
        "pass_accuracy": 71
      },
      "stats_away": {
        "shots_on_goal": 9,
        "shots_off_goal": 6,
        "total_shots": 22,
        "blocked_shots": 7,
        "corners": 7,
        "possession": 45,
        "fouls": 15,
        "yellow_cards": 1,
        "red_cards": null,
        "saves": 1,
        "total_passes": 333,
        "pass_accuracy": 69
      }
    },
    {
      "id": 157302,
      "season": 2019,
      "team_id": 71,
      "match_date": "2020-03-07T15:00:00+00:00",
      "home_team_id": 62,
      "away_team_id": 71,
      "home_team_name": "Sheffield Utd",
      "away_team_name": "Norwich",
      "goals_home": 1,
      "goals_away": 0,
      "ht_home": 1,
      "ht_away": 0,
      "status": "FT",
      "stats_home": {
        "shots_on_goal": 4,
        "shots_off_goal": 4,
        "total_shots": 10,
        "blocked_shots": 2,
        "corners": 10,
        "possession": 41,
        "fouls": 12,
        "yellow_cards": null,
        "red_cards": null,
        "saves": 4,
        "total_passes": 359,
        "pass_accuracy": 74
      },
      "stats_away": {
        "shots_on_goal": 5,
        "shots_off_goal": 4,
        "total_shots": 12,
        "blocked_shots": 3,
        "corners": 5,
        "possession": 59,
        "fouls": 8,
        "yellow_cards": null,
        "red_cards": null,
        "saves": 2,
        "total_passes": 519,
        "pass_accuracy": 81
      }
    },
    {
      "id": 157291,
      "season": 2019,
      "team_id": 71,
      "match_date": "2020-02-28T20:00:00+00:00",
      "home_team_id": 71,
      "away_team_id": 46,
      "home_team_name": "Norwich",
      "away_team_name": "Leicester",
      "goals_home": 1,
      "goals_away": 0,
      "ht_home": 0,
      "ht_away": 0,
      "status": "FT",
      "stats_home": {
        "shots_on_goal": 6,
        "shots_off_goal": 1,
        "total_shots": 11,
        "blocked_shots": 4,
        "corners": 6,
        "possession": 42,
        "fouls": 13,
        "yellow_cards": 1,
        "red_cards": null,
        "saves": 4,
        "total_passes": 344,
        "pass_accuracy": 76
      },
      "stats_away": {
        "shots_on_goal": 4,
        "shots_off_goal": 8,
        "total_shots": 19,
        "blocked_shots": 7,
        "corners": 7,
        "possession": 58,
        "fouls": 16,
        "yellow_cards": 2,
        "red_cards": null,
        "saves": 5,
        "total_passes": 468,
        "pass_accuracy": 83
      }
    },
    {
      "id": 157284,
      "season": 2019,
      "team_id": 71,
      "match_date": "2020-02-23T14:00:00+00:00",
      "home_team_id": 39,
      "away_team_id": 71,
      "home_team_name": "Wolves",
      "away_team_name": "Norwich",
      "goals_home": 3,
      "goals_away": 0,
      "ht_home": 2,
      "ht_away": 0,
      "status": "FT",
      "stats_home": {
        "shots_on_goal": 6,
        "shots_off_goal": 9,
        "total_shots": 19,
        "blocked_shots": 4,
        "corners": 4,
        "possession": 39,
        "fouls": 11,
        "yellow_cards": 2,
        "red_cards": null,
        "saves": 4,
        "total_passes": 378,
        "pass_accuracy": 77
      },
      "stats_away": {
        "shots_on_goal": 4,
        "shots_off_goal": 1,
        "total_shots": 6,
        "blocked_shots": 1,
        "corners": 1,
        "possession": 61,
        "fouls": 6,
        "yellow_cards": 3,
        "red_cards": null,
        "saves": 3,
        "total_passes": 588,
        "pass_accuracy": 85
      }
    },
    {
      "id": 157271,
      "season": 2019,
      "team_id": 71,
      "match_date": "2020-02-15T17:30:00+00:00",
      "home_team_id": 71,
      "away_team_id": 40,
      "home_team_name": "Norwich",
      "away_team_name": "Liverpool",
      "goals_home": 0,
      "goals_away": 1,
      "ht_home": 0,
      "ht_away": 0,
      "status": "FT",
      "stats_home": {
        "shots_on_goal": 1,
        "shots_off_goal": 3,
        "total_shots": 5,
        "blocked_shots": 1,
        "corners": 2,
        "possession": 36,
        "fouls": 5,
        "yellow_cards": 1,
        "red_cards": null,
        "saves": 5,
        "total_passes": 373,
        "pass_accuracy": 72
      },
      "stats_away": {
        "shots_on_goal": 6,
        "shots_off_goal": 7,
        "total_shots": 17,
        "blocked_shots": 4,
        "corners": 7,
        "possession": 64,
        "fouls": 11,
        "yellow_cards": 2,
        "red_cards": null,
        "saves": 1,
        "total_passes": 624,
        "pass_accuracy": 84
      }
    },
    {
      "id": 157261,
      "season": 2019,
      "team_id": 71,
      "match_date": "2020-02-01T15:00:00+00:00",
      "home_team_id": 34,
      "away_team_id": 71,
      "home_team_name": "Newcastle",
      "away_team_name": "Norwich",
      "goals_home": 0,
      "goals_away": 0,
      "ht_home": 0,
      "ht_away": 0,
      "status": "FT",
      "stats_home": {
        "shots_on_goal": 5,
        "shots_off_goal": 4,
        "total_shots": 15,
        "blocked_shots": 6,
        "corners": 8,
        "possession": 43,
        "fouls": 10,
        "yellow_cards": 2,
        "red_cards": null,
        "saves": 4,
        "total_passes": 365,
        "pass_accuracy": 80
      },
      "stats_away": {
        "shots_on_goal": 4,
        "shots_off_goal": 9,
        "total_shots": 19,
        "blocked_shots": 6,
        "corners": 12,
        "possession": 57,
        "fouls": 15,
        "yellow_cards": 1,
        "red_cards": null,
        "saves": 6,
        "total_passes": 485,
        "pass_accuracy": 81
      }
    },
    {
      "id": 157253,
      "season": 2019,
      "team_id": 71,
      "match_date": "2020-01-22T19:30:00+00:00",
      "home_team_id": 47,
      "away_team_id": 71,
      "home_team_name": "Tottenham",
      "away_team_name": "Norwich",
      "goals_home": 2,
      "goals_away": 1,
      "ht_home": 1,
      "ht_away": 0,
      "status": "FT",
      "stats_home": {
        "shots_on_goal": 3,
        "shots_off_goal": 5,
        "total_shots": 14,
        "blocked_shots": 6,
        "corners": 7,
        "possession": 50,
        "fouls": 12,
        "yellow_cards": 0,
        "red_cards": null,
        "saves": 1,
        "total_passes": 479,
        "pass_accuracy": 80
      },
      "stats_away": {
        "shots_on_goal": 2,
        "shots_off_goal": 7,
        "total_shots": 13,
        "blocked_shots": 4,
        "corners": 3,
        "possession": 50,
        "fouls": 7,
        "yellow_cards": 1,
        "red_cards": null,
        "saves": 1,
        "total_passes": 475,
        "pass_accuracy": 79
      }
    },
    {
      "id": 157241,
      "season": 2019,
      "team_id": 71,
      "match_date": "2020-01-18T15:00:00+00:00",
      "home_team_id": 71,
      "away_team_id": 35,
      "home_team_name": "Norwich",
      "away_team_name": "Bournemouth",
      "goals_home": 1,
      "goals_away": 0,
      "ht_home": 1,
      "ht_away": 0,
      "status": "FT",
      "stats_home": {
        "shots_on_goal": 5,
        "shots_off_goal": 5,
        "total_shots": 16,
        "blocked_shots": 6,
        "corners": 4,
        "possession": 66,
        "fouls": 10,
        "yellow_cards": 2,
        "red_cards": 1,
        "saves": 3,
        "total_passes": 635,
        "pass_accuracy": 84
      },
      "stats_away": {
        "shots_on_goal": 3,
        "shots_off_goal": 1,
        "total_shots": 6,
        "blocked_shots": 2,
        "corners": 5,
        "possession": 34,
        "fouls": 10,
        "yellow_cards": 2,
        "red_cards": 1,
        "saves": 3,
        "total_passes": 316,
        "pass_accuracy": 68
      }
    },
    {
      "id": 157231,
      "season": 2019,
      "team_id": 71,
      "match_date": "2020-01-11T15:00:00+00:00",
      "home_team_id": 33,
      "away_team_id": 71,
      "home_team_name": "Manchester United",
      "away_team_name": "Norwich",
      "goals_home": 4,
      "goals_away": 0,
      "ht_home": 1,
      "ht_away": 0,
      "status": "FT",
      "stats_home": {
        "shots_on_goal": 6,
        "shots_off_goal": 4,
        "total_shots": 13,
        "blocked_shots": 3,
        "corners": 4,
        "possession": 59,
        "fouls": 18,
        "yellow_cards": null,
        "red_cards": null,
        "saves": 3,
        "total_passes": 646,
        "pass_accuracy": 86
      },
      "stats_away": {
        "shots_on_goal": 3,
        "shots_off_goal": 2,
        "total_shots": 8,
        "blocked_shots": 3,
        "corners": 2,
        "possession": 41,
        "fouls": 7,
        "yellow_cards": null,
        "red_cards": null,
        "saves": 2,
        "total_passes": 440,
        "pass_accuracy": 79
      }
    },
    {
      "id": 157221,
      "season": 2019,
      "team_id": 71,
      "match_date": "2020-01-01T17:30:00+00:00",
      "home_team_id": 71,
      "away_team_id": 52,
      "home_team_name": "Norwich",
      "away_team_name": "Crystal Palace",
      "goals_home": 1,
      "goals_away": 1,
      "ht_home": 1,
      "ht_away": 0,
      "status": "FT",
      "stats_home": {
        "shots_on_goal": 4,
        "shots_off_goal": 8,
        "total_shots": 15,
        "blocked_shots": 3,
        "corners": 2,
        "possession": 40,
        "fouls": 12,
        "yellow_cards": 5,
        "red_cards": null,
        "saves": 2,
        "total_passes": 362,
        "pass_accuracy": 81
      },
      "stats_away": {
        "shots_on_goal": 3,
        "shots_off_goal": 4,
        "total_shots": 12,
        "blocked_shots": 5,
        "corners": 5,
        "possession": 60,
        "fouls": 9,
        "yellow_cards": 0,
        "red_cards": null,
        "saves": 3,
        "total_passes": 521,
        "pass_accuracy": 81
      }
    },
    {
      "id": 157211,
      "season": 2019,
      "team_id": 71,
      "match_date": "2019-12-28T17:30:00+00:00",
      "home_team_id": 71,
      "away_team_id": 47,
      "home_team_name": "Norwich",
      "away_team_name": "Tottenham",
      "goals_home": 2,
      "goals_away": 2,
      "ht_home": 1,
      "ht_away": 0,
      "status": "FT",
      "stats_home": {
        "shots_on_goal": 2,
        "shots_off_goal": 3,
        "total_shots": 5,
        "blocked_shots": 0,
        "corners": 4,
        "possession": 41,
        "fouls": 12,
        "yellow_cards": 3,
        "red_cards": null,
        "saves": 5,
        "total_passes": 394,
        "pass_accuracy": 71
      },
      "stats_away": {
        "shots_on_goal": 7,
        "shots_off_goal": 1,
        "total_shots": 15,
        "blocked_shots": 7,
        "corners": 6,
        "possession": 59,
        "fouls": 10,
        "yellow_cards": 3,
        "red_cards": null,
        "saves": 1,
        "total_passes": 554,
        "pass_accuracy": 81
      }
    },
    {
      "id": 157196,
      "season": 2019,
      "team_id": 71,
      "match_date": "2019-12-26T15:00:00+00:00",
      "home_team_id": 66,
      "away_team_id": 71,
      "home_team_name": "Aston Villa",
      "away_team_name": "Norwich",
      "goals_home": 1,
      "goals_away": 0,
      "ht_home": 0,
      "ht_away": 0,
      "status": "FT",
      "stats_home": {
        "shots_on_goal": 2,
        "shots_off_goal": 5,
        "total_shots": 11,
        "blocked_shots": 4,
        "corners": 5,
        "possession": 42,
        "fouls": 15,
        "yellow_cards": 2,
        "red_cards": null,
        "saves": 5,
        "total_passes": 363,
        "pass_accuracy": 75
      },
      "stats_away": {
        "shots_on_goal": 6,
        "shots_off_goal": 6,
        "total_shots": 16,
        "blocked_shots": 4,
        "corners": 8,
        "possession": 58,
        "fouls": 12,
        "yellow_cards": 3,
        "red_cards": null,
        "saves": 1,
        "total_passes": 508,
        "pass_accuracy": 83
      }
    },
    {
      "id": 157191,
      "season": 2019,
      "team_id": 71,
      "match_date": "2019-12-21T15:00:00+00:00",
      "home_team_id": 71,
      "away_team_id": 39,
      "home_team_name": "Norwich",
      "away_team_name": "Wolves",
      "goals_home": 1,
      "goals_away": 2,
      "ht_home": 1,
      "ht_away": 0,
      "status": "FT",
      "stats_home": {
        "shots_on_goal": 7,
        "shots_off_goal": 5,
        "total_shots": 13,
        "blocked_shots": 1,
        "corners": 3,
        "possession": 50,
        "fouls": 7,
        "yellow_cards": 2,
        "red_cards": null,
        "saves": 2,
        "total_passes": 455,
        "pass_accuracy": 80
      },
      "stats_away": {
        "shots_on_goal": 4,
        "shots_off_goal": 2,
        "total_shots": 14,
        "blocked_shots": 8,
        "corners": 11,
        "possession": 50,
        "fouls": 14,
        "yellow_cards": 4,
        "red_cards": null,
        "saves": 6,
        "total_passes": 440,
        "pass_accuracy": 81
      }
    },
    {
      "id": 157179,
      "season": 2019,
      "team_id": 71,
      "match_date": "2019-12-14T15:00:00+00:00",
      "home_team_id": 46,
      "away_team_id": 71,
      "home_team_name": "Leicester",
      "away_team_name": "Norwich",
      "goals_home": 1,
      "goals_away": 1,
      "ht_home": 1,
      "ht_away": 1,
      "status": "FT",
      "stats_home": {
        "shots_on_goal": 5,
        "shots_off_goal": 8,
        "total_shots": 18,
        "blocked_shots": 5,
        "corners": 12,
        "possession": 56,
        "fouls": 11,
        "yellow_cards": 0,
        "red_cards": null,
        "saves": 2,
        "total_passes": 513,
        "pass_accuracy": 84
      },
      "stats_away": {
        "shots_on_goal": 3,
        "shots_off_goal": 3,
        "total_shots": 10,
        "blocked_shots": 4,
        "corners": 4,
        "possession": 44,
        "fouls": 15,
        "yellow_cards": 5,
        "red_cards": null,
        "saves": 5,
        "total_passes": 397,
        "pass_accuracy": 79
      }
    },
    {
      "id": 157171,
      "season": 2019,
      "team_id": 71,
      "match_date": "2019-12-08T14:00:00+00:00",
      "home_team_id": 71,
      "away_team_id": 62,
      "home_team_name": "Norwich",
      "away_team_name": "Sheffield Utd",
      "goals_home": 1,
      "goals_away": 2,
      "ht_home": 1,
      "ht_away": 0,
      "status": "FT",
      "stats_home": {
        "shots_on_goal": 4,
        "shots_off_goal": 5,
        "total_shots": 14,
        "blocked_shots": 5,
        "corners": 9,
        "possession": 58,
        "fouls": 6,
        "yellow_cards": 0,
        "red_cards": null,
        "saves": 1,
        "total_passes": 579,
        "pass_accuracy": 78
      },
      "stats_away": {
        "shots_on_goal": 3,
        "shots_off_goal": 5,
        "total_shots": 9,
        "blocked_shots": 1,
        "corners": 1,
        "possession": 42,
        "fouls": 12,
        "yellow_cards": 4,
        "red_cards": null,
        "saves": 3,
        "total_passes": 418,
        "pass_accuracy": 70
      }
    },
    {
      "id": 157162,
      "season": 2019,
      "team_id": 71,
      "match_date": "2019-12-04T19:30:00+00:00",
      "home_team_id": 41,
      "away_team_id": 71,
      "home_team_name": "Southampton",
      "away_team_name": "Norwich",
      "goals_home": 2,
      "goals_away": 1,
      "ht_home": 2,
      "ht_away": 0,
      "status": "FT",
      "stats_home": {
        "shots_on_goal": 5,
        "shots_off_goal": 5,
        "total_shots": 14,
        "blocked_shots": 4,
        "corners": 6,
        "possession": 40,
        "fouls": 12,
        "yellow_cards": 1,
        "red_cards": null,
        "saves": 2,
        "total_passes": 366,
        "pass_accuracy": 69
      },
      "stats_away": {
        "shots_on_goal": 3,
        "shots_off_goal": 5,
        "total_shots": 10,
        "blocked_shots": 2,
        "corners": 1,
        "possession": 60,
        "fouls": 7,
        "yellow_cards": 1,
        "red_cards": null,
        "saves": 3,
        "total_passes": 562,
        "pass_accuracy": 79
      }
    },
    {
      "id": 157151,
      "season": 2019,
      "team_id": 71,
      "match_date": "2019-12-01T14:00:00+00:00",
      "home_team_id": 71,
      "away_team_id": 42,
      "home_team_name": "Norwich",
      "away_team_name": "Arsenal",
      "goals_home": 2,
      "goals_away": 2,
      "ht_home": 2,
      "ht_away": 1,
      "status": "FT",
      "stats_home": {
        "shots_on_goal": 8,
        "shots_off_goal": 5,
        "total_shots": 15,
        "blocked_shots": 2,
        "corners": 7,
        "possession": 39,
        "fouls": 8,
        "yellow_cards": 2,
        "red_cards": null,
        "saves": 4,
        "total_passes": 364,
        "pass_accuracy": 80
      },
      "stats_away": {
        "shots_on_goal": 7,
        "shots_off_goal": 1,
        "total_shots": 16,
        "blocked_shots": 8,
        "corners": 12,
        "possession": 61,
        "fouls": 10,
        "yellow_cards": 1,
        "red_cards": null,
        "saves": 6,
        "total_passes": 541,
        "pass_accuracy": 85
      }
    },
    {
      "id": 157140,
      "season": 2019,
      "team_id": 71,
      "match_date": "2019-11-23T15:00:00+00:00",
      "home_team_id": 45,
      "away_team_id": 71,
      "home_team_name": "Everton",
      "away_team_name": "Norwich",
      "goals_home": 0,
      "goals_away": 2,
      "ht_home": 0,
      "ht_away": 0,
      "status": "FT",
      "stats_home": {
        "shots_on_goal": 7,
        "shots_off_goal": 7,
        "total_shots": 18,
        "blocked_shots": 4,
        "corners": 7,
        "possession": 57,
        "fouls": 12,
        "yellow_cards": 3,
        "red_cards": null,
        "saves": 3,
        "total_passes": 401,
        "pass_accuracy": 76
      },
      "stats_away": {
        "shots_on_goal": 5,
        "shots_off_goal": 3,
        "total_shots": 13,
        "blocked_shots": 5,
        "corners": 7,
        "possession": 43,
        "fouls": 11,
        "yellow_cards": 5,
        "red_cards": null,
        "saves": 7,
        "total_passes": 307,
        "pass_accuracy": 71
      }
    },
    {
      "id": 157131,
      "season": 2019,
      "team_id": 71,
      "match_date": "2019-11-08T20:00:00+00:00",
      "home_team_id": 71,
      "away_team_id": 38,
      "home_team_name": "Norwich",
      "away_team_name": "Watford",
      "goals_home": 0,
      "goals_away": 2,
      "ht_home": 0,
      "ht_away": 1,
      "status": "FT",
      "stats_home": {
        "shots_on_goal": 5,
        "shots_off_goal": 7,
        "total_shots": 17,
        "blocked_shots": 5,
        "corners": 10,
        "possession": 65,
        "fouls": 7,
        "yellow_cards": 1,
        "red_cards": 0,
        "saves": 0,
        "total_passes": 597,
        "pass_accuracy": 88
      },
      "stats_away": {
        "shots_on_goal": 2,
        "shots_off_goal": 6,
        "total_shots": 12,
        "blocked_shots": 4,
        "corners": 4,
        "possession": 35,
        "fouls": 13,
        "yellow_cards": 4,
        "red_cards": 1,
        "saves": 5,
        "total_passes": 315,
        "pass_accuracy": 74
      }
    },
    {
      "id": 157118,
      "season": 2019,
      "team_id": 71,
      "match_date": "2019-11-02T15:00:00+00:00",
      "home_team_id": 51,
      "away_team_id": 71,
      "home_team_name": "Brighton",
      "away_team_name": "Norwich",
      "goals_home": 2,
      "goals_away": 0,
      "ht_home": 0,
      "ht_away": 0,
      "status": "FT",
      "stats_home": {
        "shots_on_goal": 5,
        "shots_off_goal": 12,
        "total_shots": 21,
        "blocked_shots": 4,
        "corners": 8,
        "possession": 58,
        "fouls": 11,
        "yellow_cards": 0,
        "red_cards": null,
        "saves": 0,
        "total_passes": 538,
        "pass_accuracy": 84
      },
      "stats_away": {
        "shots_on_goal": 0,
        "shots_off_goal": 4,
        "total_shots": 7,
        "blocked_shots": 3,
        "corners": 3,
        "possession": 42,
        "fouls": 8,
        "yellow_cards": 1,
        "red_cards": null,
        "saves": 3,
        "total_passes": 391,
        "pass_accuracy": 79
      }
    },
    {
      "id": 157111,
      "season": 2019,
      "team_id": 71,
      "match_date": "2019-10-27T15:30:00+00:00",
      "home_team_id": 71,
      "away_team_id": 33,
      "home_team_name": "Norwich",
      "away_team_name": "Manchester United",
      "goals_home": 1,
      "goals_away": 3,
      "ht_home": 0,
      "ht_away": 2,
      "status": "FT",
      "stats_home": {
        "shots_on_goal": 3,
        "shots_off_goal": 5,
        "total_shots": 10,
        "blocked_shots": 2,
        "corners": 1,
        "possession": 46,
        "fouls": 13,
        "yellow_cards": 2,
        "red_cards": null,
        "saves": 8,
        "total_passes": 417,
        "pass_accuracy": 79
      },
      "stats_away": {
        "shots_on_goal": 11,
        "shots_off_goal": 7,
        "total_shots": 21,
        "blocked_shots": 3,
        "corners": 10,
        "possession": 54,
        "fouls": 10,
        "yellow_cards": 2,
        "red_cards": null,
        "saves": 2,
        "total_passes": 480,
        "pass_accuracy": 85
      }
    },
    {
      "id": 157095,
      "season": 2019,
      "team_id": 71,
      "match_date": "2019-10-19T14:00:00+00:00",
      "home_team_id": 35,
      "away_team_id": 71,
      "home_team_name": "Bournemouth",
      "away_team_name": "Norwich",
      "goals_home": 0,
      "goals_away": 0,
      "ht_home": 0,
      "ht_away": 0,
      "status": "FT",
      "stats_home": {
        "shots_on_goal": 2,
        "shots_off_goal": 6,
        "total_shots": 11,
        "blocked_shots": 3,
        "corners": 6,
        "possession": 47,
        "fouls": 8,
        "yellow_cards": 1,
        "red_cards": null,
        "saves": 1,
        "total_passes": 407,
        "pass_accuracy": 80
      },
      "stats_away": {
        "shots_on_goal": 1,
        "shots_off_goal": 6,
        "total_shots": 10,
        "blocked_shots": 3,
        "corners": 7,
        "possession": 53,
        "fouls": 11,
        "yellow_cards": 3,
        "red_cards": null,
        "saves": 2,
        "total_passes": 469,
        "pass_accuracy": 81
      }
    },
    {
      "id": 157091,
      "season": 2019,
      "team_id": 71,
      "match_date": "2019-10-05T14:00:00+00:00",
      "home_team_id": 71,
      "away_team_id": 66,
      "home_team_name": "Norwich",
      "away_team_name": "Aston Villa",
      "goals_home": 1,
      "goals_away": 5,
      "ht_home": 0,
      "ht_away": 2,
      "status": "FT",
      "stats_home": {
        "shots_on_goal": 5,
        "shots_off_goal": 8,
        "total_shots": 21,
        "blocked_shots": 8,
        "corners": 10,
        "possession": 57,
        "fouls": 14,
        "yellow_cards": 1,
        "red_cards": null,
        "saves": 7,
        "total_passes": 472,
        "pass_accuracy": 81
      },
      "stats_away": {
        "shots_on_goal": 12,
        "shots_off_goal": 7,
        "total_shots": 22,
        "blocked_shots": 3,
        "corners": 6,
        "possession": 43,
        "fouls": 17,
        "yellow_cards": 3,
        "red_cards": null,
        "saves": 4,
        "total_passes": 345,
        "pass_accuracy": 78
      }
    },
    {
      "id": 157078,
      "season": 2019,
      "team_id": 71,
      "match_date": "2019-09-28T14:00:00+00:00",
      "home_team_id": 52,
      "away_team_id": 71,
      "home_team_name": "Crystal Palace",
      "away_team_name": "Norwich",
      "goals_home": 2,
      "goals_away": 0,
      "ht_home": 1,
      "ht_away": 0,
      "status": "FT",
      "stats_home": {
        "shots_on_goal": 3,
        "shots_off_goal": 6,
        "total_shots": 15,
        "blocked_shots": 6,
        "corners": 5,
        "possession": 44,
        "fouls": 14,
        "yellow_cards": 3,
        "red_cards": null,
        "saves": 3,
        "total_passes": 415,
        "pass_accuracy": 80
      },
      "stats_away": {
        "shots_on_goal": 3,
        "shots_off_goal": 2,
        "total_shots": 10,
        "blocked_shots": 5,
        "corners": 5,
        "possession": 56,
        "fouls": 10,
        "yellow_cards": 1,
        "red_cards": null,
        "saves": 1,
        "total_passes": 524,
        "pass_accuracy": 84
      }
    },
    {
      "id": 157066,
      "season": 2019,
      "team_id": 71,
      "match_date": "2019-09-21T14:00:00+00:00",
      "home_team_id": 44,
      "away_team_id": 71,
      "home_team_name": "Burnley",
      "away_team_name": "Norwich",
      "goals_home": 2,
      "goals_away": 0,
      "ht_home": 2,
      "ht_away": 0,
      "status": "FT",
      "stats_home": {
        "shots_on_goal": 6,
        "shots_off_goal": 2,
        "total_shots": 13,
        "blocked_shots": 5,
        "corners": 7,
        "possession": 41,
        "fouls": 11,
        "yellow_cards": 0,
        "red_cards": null,
        "saves": 2,
        "total_passes": 357,
        "pass_accuracy": 76
      },
      "stats_away": {
        "shots_on_goal": 2,
        "shots_off_goal": 6,
        "total_shots": 11,
        "blocked_shots": 3,
        "corners": 3,
        "possession": 59,
        "fouls": 10,
        "yellow_cards": 1,
        "red_cards": null,
        "saves": 4,
        "total_passes": 528,
        "pass_accuracy": 83
      }
    },
    {
      "id": 157060,
      "season": 2019,
      "team_id": 71,
      "match_date": "2019-09-14T16:30:00+00:00",
      "home_team_id": 71,
      "away_team_id": 50,
      "home_team_name": "Norwich",
      "away_team_name": "Manchester City",
      "goals_home": 3,
      "goals_away": 2,
      "ht_home": 2,
      "ht_away": 1,
      "status": "FT",
      "stats_home": {
        "shots_on_goal": 3,
        "shots_off_goal": 3,
        "total_shots": 7,
        "blocked_shots": 1,
        "corners": 3,
        "possession": 31,
        "fouls": 8,
        "yellow_cards": 3,
        "red_cards": null,
        "saves": 6,
        "total_passes": 318,
        "pass_accuracy": 74
      },
      "stats_away": {
        "shots_on_goal": 8,
        "shots_off_goal": 6,
        "total_shots": 25,
        "blocked_shots": 11,
        "corners": 16,
        "possession": 69,
        "fouls": 7,
        "yellow_cards": 1,
        "red_cards": null,
        "saves": 0,
        "total_passes": 671,
        "pass_accuracy": 89
      }
    },
    {
      "id": 157054,
      "season": 2019,
      "team_id": 71,
      "match_date": "2019-08-31T14:00:00+00:00",
      "home_team_id": 48,
      "away_team_id": 71,
      "home_team_name": "West Ham",
      "away_team_name": "Norwich",
      "goals_home": 2,
      "goals_away": 0,
      "ht_home": 1,
      "ht_away": 0,
      "status": "FT",
      "stats_home": {
        "shots_on_goal": 8,
        "shots_off_goal": 7,
        "total_shots": 18,
        "blocked_shots": 3,
        "corners": 8,
        "possession": 48,
        "fouls": 16,
        "yellow_cards": 2,
        "red_cards": null,
        "saves": 3,
        "total_passes": 474,
        "pass_accuracy": 83
      },
      "stats_away": {
        "shots_on_goal": 3,
        "shots_off_goal": 3,
        "total_shots": 8,
        "blocked_shots": 2,
        "corners": 2,
        "possession": 52,
        "fouls": 10,
        "yellow_cards": 1,
        "red_cards": null,
        "saves": 5,
        "total_passes": 500,
        "pass_accuracy": 87
      }
    },
    {
      "id": 157040,
      "season": 2019,
      "team_id": 71,
      "match_date": "2019-08-24T11:30:00+00:00",
      "home_team_id": 71,
      "away_team_id": 49,
      "home_team_name": "Norwich",
      "away_team_name": "Chelsea",
      "goals_home": 2,
      "goals_away": 3,
      "ht_home": 2,
      "ht_away": 2,
      "status": "FT",
      "stats_home": {
        "shots_on_goal": 5,
        "shots_off_goal": 1,
        "total_shots": 6,
        "blocked_shots": 0,
        "corners": 1,
        "possession": 46,
        "fouls": 9,
        "yellow_cards": 1,
        "red_cards": null,
        "saves": 5,
        "total_passes": 481,
        "pass_accuracy": 81
      },
      "stats_away": {
        "shots_on_goal": 8,
        "shots_off_goal": 5,
        "total_shots": 23,
        "blocked_shots": 10,
        "corners": 8,
        "possession": 54,
        "fouls": 9,
        "yellow_cards": 1,
        "red_cards": null,
        "saves": 3,
        "total_passes": 543,
        "pass_accuracy": 84
      }
    },
    {
      "id": 157031,
      "season": 2019,
      "team_id": 71,
      "match_date": "2019-08-17T14:00:00+00:00",
      "home_team_id": 71,
      "away_team_id": 34,
      "home_team_name": "Norwich",
      "away_team_name": "Newcastle",
      "goals_home": 3,
      "goals_away": 1,
      "ht_home": 1,
      "ht_away": 0,
      "status": "FT",
      "stats_home": {
        "shots_on_goal": 8,
        "shots_off_goal": 3,
        "total_shots": 15,
        "blocked_shots": 4,
        "corners": 7,
        "possession": 63,
        "fouls": 9,
        "yellow_cards": 1,
        "red_cards": null,
        "saves": 3,
        "total_passes": 603,
        "pass_accuracy": 88
      },
      "stats_away": {
        "shots_on_goal": 4,
        "shots_off_goal": 7,
        "total_shots": 12,
        "blocked_shots": 1,
        "corners": 5,
        "possession": 37,
        "fouls": 11,
        "yellow_cards": 3,
        "red_cards": null,
        "saves": 5,
        "total_passes": 336,
        "pass_accuracy": 81
      }
    },
    {
      "id": 157015,
      "season": 2019,
      "team_id": 71,
      "match_date": "2019-08-09T19:00:00+00:00",
      "home_team_id": 40,
      "away_team_id": 71,
      "home_team_name": "Liverpool",
      "away_team_name": "Norwich",
      "goals_home": 4,
      "goals_away": 1,
      "ht_home": 4,
      "ht_away": 0,
      "status": "FT",
      "stats_home": {
        "shots_on_goal": 7,
        "shots_off_goal": 5,
        "total_shots": 15,
        "blocked_shots": 3,
        "corners": 11,
        "possession": 57,
        "fouls": 9,
        "yellow_cards": 0,
        "red_cards": null,
        "saves": 4,
        "total_passes": 477,
        "pass_accuracy": 81
      },
      "stats_away": {
        "shots_on_goal": 5,
        "shots_off_goal": 5,
        "total_shots": 12,
        "blocked_shots": 2,
        "corners": 2,
        "possession": 43,
        "fouls": 9,
        "yellow_cards": 2,
        "red_cards": null,
        "saves": 4,
        "total_passes": 363,
        "pass_accuracy": 77
      }
    }
  ]
}