{
  "teamId": 38,
  "season": 2021,
  "byTimeAvailable": false,
  "scored": {
    "total": 34,
    "byTime": null
  },
  "conceded": {
    "total": 77,
    "byTime": null
  },
  "home": {
    "scored": {
      "total": null,
      "byTime": null
    },
    "conceded": {
      "total": null,
      "byTime": null
    }
  },
  "away": {
    "scored": {
      "total": null,
      "byTime": null
    },
    "conceded": {
      "total": null,
      "byTime": null
    }
  },
  "recentForm": [
    "L",
    "L",
    "D",
    "L",
    "L"
  ],
  "scorers": [
    {
      "id": 80,
      "name": "E. Dennis",
      "photo": "https://media.api-sports.io/football/players/80.png",
      "goals": 10,
      "assists": 6,
      "appearances": 33
    },
    {
      "id": 2218,
      "name": "I. Sarr",
      "photo": "https://media.api-sports.io/football/players/2218.png",
      "goals": 5,
      "assists": 2,
      "appearances": 22
    },
    {
      "id": 47582,
      "name": "C. Hernández",
      "photo": "https://media.api-sports.io/football/players/47582.png",
      "goals": 5,
      "assists": 2,
      "appearances": 25
    },
    {
      "id": 18881,
      "name": "J. King",
      "photo": "https://media.api-sports.io/football/players/18881.png",
      "goals": 5,
      "assists": 3,
      "appearances": 32
    },
    {
      "id": 10329,
      "name": "João Pedro",
      "photo": "https://media.api-sports.io/football/players/10329.png",
      "goals": 3,
      "assists": 1,
      "appearances": 28
    },
    {
      "id": 179,
      "name": "M. Sissoko",
      "photo": "https://media.api-sports.io/football/players/179.png",
      "goals": 2,
      "assists": 0,
      "appearances": 36
    },
    {
      "id": 18874,
      "name": "D. Gosling",
      "photo": "https://media.api-sports.io/football/players/18874.png",
      "goals": 1,
      "assists": 0,
      "appearances": 4
    },
    {
      "id": 22007,
      "name": "H. Kamara",
      "photo": "https://media.api-sports.io/football/players/22007.png",
      "goals": 1,
      "assists": 0,
      "appearances": 19
    },
    {
      "id": 31023,
      "name": "J. Kucka",
      "photo": "https://media.api-sports.io/football/players/31023.png",
      "goals": 1,
      "assists": 1,
      "appearances": 26
    }
  ],
  "fixtures": [
    {
      "id": 710930,
      "season": 2021,
      "team_id": 38,
      "match_date": "2022-05-22T15:00:00+00:00",
      "home_team_id": 49,
      "away_team_id": 38,
      "home_team_name": "Chelsea",
      "away_team_name": "Watford",
      "goals_home": 2,
      "goals_away": 1,
      "ht_home": 1,
      "ht_away": 0,
      "status": "FT"
    },
    {
      "id": 710923,
      "season": 2021,
      "team_id": 38,
      "match_date": "2022-05-15T13:00:00+00:00",
      "home_team_id": 38,
      "away_team_id": 46,
      "home_team_name": "Watford",
      "away_team_name": "Leicester",
      "goals_home": 1,
      "goals_away": 5,
      "ht_home": 1,
      "ht_away": 2,
      "status": "FT"
    },
    {
      "id": 710854,
      "season": 2021,
      "team_id": 38,
      "match_date": "2022-05-11T18:45:00+00:00",
      "home_team_id": 38,
      "away_team_id": 45,
      "home_team_name": "Watford",
      "away_team_name": "Everton",
      "goals_home": 0,
      "goals_away": 0,
      "ht_home": 0,
      "ht_away": 0,
      "status": "FT"
    },
    {
      "id": 710911,
      "season": 2021,
      "team_id": 38,
      "match_date": "2022-05-07T14:00:00+00:00",
      "home_team_id": 52,
      "away_team_id": 38,
      "home_team_name": "Crystal Palace",
      "away_team_name": "Watford",
      "goals_home": 1,
      "goals_away": 0,
      "ht_home": 1,
      "ht_away": 0,
      "status": "FT"
    },
    {
      "id": 710903,
      "season": 2021,
      "team_id": 38,
      "match_date": "2022-04-30T14:00:00+00:00",
      "home_team_id": 38,
      "away_team_id": 44,
      "home_team_name": "Watford",
      "away_team_name": "Burnley",
      "goals_home": 1,
      "goals_away": 2,
      "ht_home": 1,
      "ht_away": 0,
      "status": "FT"
    },
    {
      "id": 710894,
      "season": 2021,
      "team_id": 38,
      "match_date": "2022-04-23T14:00:00+00:00",
      "home_team_id": 50,
      "away_team_id": 38,
      "home_team_name": "Manchester City",
      "away_team_name": "Watford",
      "goals_home": 5,
      "goals_away": 1,
      "ht_home": 3,
      "ht_away": 1,
      "status": "FT"
    },
    {
      "id": 710883,
      "season": 2021,
      "team_id": 38,
      "match_date": "2022-04-16T14:00:00+00:00",
      "home_team_id": 38,
      "away_team_id": 55,
      "home_team_name": "Watford",
      "away_team_name": "Brentford",
      "goals_home": 1,
      "goals_away": 2,
      "ht_home": 0,
      "ht_away": 1,
      "status": "FT"
    },
    {
      "id": 710875,
      "season": 2021,
      "team_id": 38,
      "match_date": "2022-04-09T14:00:00+00:00",
      "home_team_id": 38,
      "away_team_id": 63,
      "home_team_name": "Watford",
      "away_team_name": "Leeds",
      "goals_home": 0,
      "goals_away": 3,
      "ht_home": 0,
      "ht_away": 1,
      "status": "FT"
    },
    {
      "id": 710861,
      "season": 2021,
      "team_id": 38,
      "match_date": "2022-04-02T11:30:00+00:00",
      "home_team_id": 40,
      "away_team_id": 38,
      "home_team_name": "Liverpool",
      "away_team_name": "Watford",
      "goals_home": 2,
      "goals_away": 0,
      "ht_home": 1,
      "ht_away": 0,
      "status": "FT"
    },
    {
      "id": 710844,
      "season": 2021,
      "team_id": 38,
      "match_date": "2022-03-13T14:00:00+00:00",
      "home_team_id": 41,
      "away_team_id": 38,
      "home_team_name": "Southampton",
      "away_team_name": "Watford",
      "goals_home": 1,
      "goals_away": 2,
      "ht_home": 1,
      "ht_away": 2,
      "status": "FT"
    },
    {
      "id": 710745,
      "season": 2021,
      "team_id": 38,
      "match_date": "2022-03-10T19:30:00+00:00",
      "home_team_id": 39,
      "away_team_id": 38,
      "home_team_name": "Wolves",
      "away_team_name": "Watford",
      "goals_home": 4,
      "goals_away": 0,
      "ht_home": 3,
      "ht_away": 0,
      "status": "FT"
    },
    {
      "id": 710834,
      "season": 2021,
      "team_id": 38,
      "match_date": "2022-03-06T14:00:00+00:00",
      "home_team_id": 38,
      "away_team_id": 42,
      "home_team_name": "Watford",
      "away_team_name": "Arsenal",
      "goals_home": 2,
      "goals_away": 3,
      "ht_home": 1,
      "ht_away": 2,
      "status": "FT"
    },
    {
      "id": 710823,
      "season": 2021,
      "team_id": 38,
      "match_date": "2022-02-26T15:00:00+00:00",
      "home_team_id": 33,
      "away_team_id": 38,
      "home_team_name": "Manchester United",
      "away_team_name": "Watford",
      "goals_home": 0,
      "goals_away": 0,
      "ht_home": 0,
      "ht_away": 0,
      "status": "FT"
    },
    {
      "id": 710733,
      "season": 2021,
      "team_id": 38,
      "match_date": "2022-02-23T19:30:00+00:00",
      "home_team_id": 38,
      "away_team_id": 52,
      "home_team_name": "Watford",
      "away_team_name": "Crystal Palace",
      "goals_home": 1,
      "goals_away": 4,
      "ht_home": 1,
      "ht_away": 2,
      "status": "FT"
    },
    {
      "id": 710807,
      "season": 2021,
      "team_id": 38,
      "match_date": "2022-02-19T15:00:00+00:00",
      "home_team_id": 66,
      "away_team_id": 38,
      "home_team_name": "Aston Villa",
      "away_team_name": "Watford",
      "goals_home": 0,
      "goals_away": 1,
      "ht_home": 0,
      "ht_away": 0,
      "status": "FT"
    },
    {
      "id": 710805,
      "season": 2021,
      "team_id": 38,
      "match_date": "2022-02-12T15:00:00+00:00",
      "home_team_id": 38,
      "away_team_id": 51,
      "home_team_name": "Watford",
      "away_team_name": "Brighton",
      "goals_home": 0,
      "goals_away": 2,
      "ht_home": 0,
      "ht_away": 1,
      "status": "FT"
    },
    {
      "id": 710790,
      "season": 2021,
      "team_id": 38,
      "match_date": "2022-02-08T19:45:00+00:00",
      "home_team_id": 48,
      "away_team_id": 38,
      "home_team_name": "West Ham",
      "away_team_name": "Watford",
      "goals_home": 1,
      "goals_away": 0,
      "ht_home": 0,
      "ht_away": 0,
      "status": "FT"
    },
    {
      "id": 710719,
      "season": 2021,
      "team_id": 38,
      "match_date": "2022-02-05T18:00:00+00:00",
      "home_team_id": 44,
      "away_team_id": 38,
      "home_team_name": "Burnley",
      "away_team_name": "Watford",
      "goals_home": 0,
      "goals_away": 0,
      "ht_home": 0,
      "ht_away": 0,
      "status": "FT"
    },
    {
      "id": 710785,
      "season": 2021,
      "team_id": 38,
      "match_date": "2022-01-21T20:00:00+00:00",
      "home_team_id": 38,
      "away_team_id": 71,
      "home_team_name": "Watford",
      "away_team_name": "Norwich",
      "goals_home": 0,
      "goals_away": 3,
      "ht_home": 0,
      "ht_away": 0,
      "status": "FT"
    },
    {
      "id": 710771,
      "season": 2021,
      "team_id": 38,
      "match_date": "2022-01-15T15:00:00+00:00",
      "home_team_id": 34,
      "away_team_id": 38,
      "home_team_name": "Newcastle",
      "away_team_name": "Watford",
      "goals_home": 1,
      "goals_away": 1,
      "ht_home": 0,
      "ht_away": 0,
      "status": "FT"
    },
    {
      "id": 710765,
      "season": 2021,
      "team_id": 38,
      "match_date": "2022-01-01T15:00:00+00:00",
      "home_team_id": 38,
      "away_team_id": 47,
      "home_team_name": "Watford",
      "away_team_name": "Tottenham",
      "goals_home": 0,
      "goals_away": 1,
      "ht_home": 0,
      "ht_away": 0,
      "status": "FT"
    },
    {
      "id": 710755,
      "season": 2021,
      "team_id": 38,
      "match_date": "2021-12-28T15:00:00+00:00",
      "home_team_id": 38,
      "away_team_id": 48,
      "home_team_name": "Watford",
      "away_team_name": "West Ham",
      "goals_home": 1,
      "goals_away": 4,
      "ht_home": 1,
      "ht_away": 2,
      "status": "FT"
    },
    {
      "id": 710707,
      "season": 2021,
      "team_id": 38,
      "match_date": "2021-12-10T20:00:00+00:00",
      "home_team_id": 55,
      "away_team_id": 38,
      "home_team_name": "Brentford",
      "away_team_name": "Watford",
      "goals_home": 2,
      "goals_away": 1,
      "ht_home": 0,
      "ht_away": 1,
      "status": "FT"
    },
    {
      "id": 710703,
      "season": 2021,
      "team_id": 38,
      "match_date": "2021-12-04T17:30:00+00:00",
      "home_team_id": 38,
      "away_team_id": 50,
      "home_team_name": "Watford",
      "away_team_name": "Manchester City",
      "goals_home": 1,
      "goals_away": 3,
      "ht_home": 0,
      "ht_away": 2,
      "status": "FT"
    },
    {
      "id": 710689,
      "season": 2021,
      "team_id": 38,
      "match_date": "2021-12-01T19:30:00+00:00",
      "home_team_id": 38,
      "away_team_id": 49,
      "home_team_name": "Watford",
      "away_team_name": "Chelsea",
      "goals_home": 1,
      "goals_away": 2,
      "ht_home": 1,
      "ht_away": 1,
      "status": "FT"
    },
    {
      "id": 710682,
      "season": 2021,
      "team_id": 38,
      "match_date": "2021-11-28T14:00:00+00:00",
      "home_team_id": 46,
      "away_team_id": 38,
      "home_team_name": "Leicester",
      "away_team_name": "Watford",
      "goals_home": 4,
      "goals_away": 2,
      "ht_home": 3,
      "ht_away": 1,
      "status": "FT"
    },
    {
      "id": 710674,
      "season": 2021,
      "team_id": 38,
      "match_date": "2021-11-20T15:00:00+00:00",
      "home_team_id": 38,
      "away_team_id": 33,
      "home_team_name": "Watford",
      "away_team_name": "Manchester United",
      "goals_home": 4,
      "goals_away": 1,
      "ht_home": 2,
      "ht_away": 0,
      "status": "FT"
    },
    {
      "id": 710656,
      "season": 2021,
      "team_id": 38,
      "match_date": "2021-11-07T14:00:00+00:00",
      "home_team_id": 42,
      "away_team_id": 38,
      "home_team_name": "Arsenal",
      "away_team_name": "Watford",
      "goals_home": 1,
      "goals_away": 0,
      "ht_home": 0,
      "ht_away": 0,
      "status": "FT"
    },
    {
      "id": 710654,
      "season": 2021,
      "team_id": 38,
      "match_date": "2021-10-30T14:00:00+00:00",
      "home_team_id": 38,
      "away_team_id": 41,
      "home_team_name": "Watford",
      "away_team_name": "Southampton",
      "goals_home": 0,
      "goals_away": 1,
      "ht_home": 0,
      "ht_away": 1,
      "status": "FT"
    },
    {
      "id": 710641,
      "season": 2021,
      "team_id": 38,
      "match_date": "2021-10-23T14:00:00+00:00",
      "home_team_id": 45,
      "away_team_id": 38,
      "home_team_name": "Everton",
      "away_team_name": "Watford",
      "goals_home": 2,
      "goals_away": 5,
      "ht_home": 1,
      "ht_away": 1,
      "status": "FT"
    },
    {
      "id": 710635,
      "season": 2021,
      "team_id": 38,
      "match_date": "2021-10-16T11:30:00+00:00",
      "home_team_id": 38,
      "away_team_id": 40,
      "home_team_name": "Watford",
      "away_team_name": "Liverpool",
      "goals_home": 0,
      "goals_away": 5,
      "ht_home": 0,
      "ht_away": 2,
      "status": "FT"
    },
    {
      "id": 710620,
      "season": 2021,
      "team_id": 38,
      "match_date": "2021-10-02T14:00:00+00:00",
      "home_team_id": 63,
      "away_team_id": 38,
      "home_team_name": "Leeds",
      "away_team_name": "Watford",
      "goals_home": 1,
      "goals_away": 0,
      "ht_home": 1,
      "ht_away": 0,
      "status": "FT"
    },
    {
      "id": 710615,
      "season": 2021,
      "team_id": 38,
      "match_date": "2021-09-25T14:00:00+00:00",
      "home_team_id": 38,
      "away_team_id": 34,
      "home_team_name": "Watford",
      "away_team_name": "Newcastle",
      "goals_home": 1,
      "goals_away": 1,
      "ht_home": 0,
      "ht_away": 1,
      "status": "FT"
    },
    {
      "id": 710602,
      "season": 2021,
      "team_id": 38,
      "match_date": "2021-09-18T14:00:00+00:00",
      "home_team_id": 71,
      "away_team_id": 38,
      "home_team_name": "Norwich",
      "away_team_name": "Watford",
      "goals_home": 1,
      "goals_away": 3,
      "ht_home": 1,
      "ht_away": 1,
      "status": "FT"
    },
    {
      "id": 710595,
      "season": 2021,
      "team_id": 38,
      "match_date": "2021-09-11T14:00:00+00:00",
      "home_team_id": 38,
      "away_team_id": 39,
      "home_team_name": "Watford",
      "away_team_name": "Wolves",
      "goals_home": 0,
      "goals_away": 2,
      "ht_home": 0,
      "ht_away": 0,
      "status": "FT"
    },
    {
      "id": 710583,
      "season": 2021,
      "team_id": 38,
      "match_date": "2021-08-29T13:00:00+00:00",
      "home_team_id": 47,
      "away_team_id": 38,
      "home_team_name": "Tottenham",
      "away_team_name": "Watford",
      "goals_home": 1,
      "goals_away": 0,
      "ht_home": 1,
      "ht_away": 0,
      "status": "FT"
    },
    {
      "id": 710568,
      "season": 2021,
      "team_id": 38,
      "match_date": "2021-08-21T16:30:00+00:00",
      "home_team_id": 51,
      "away_team_id": 38,
      "home_team_name": "Brighton",
      "away_team_name": "Watford",
      "goals_home": 2,
      "goals_away": 0,
      "ht_home": 2,
      "ht_away": 0,
      "status": "FT"
    },
    {
      "id": 710565,
      "season": 2021,
      "team_id": 38,
      "match_date": "2021-08-14T14:00:00+00:00",
      "home_team_id": 38,
      "away_team_id": 66,
      "home_team_name": "Watford",
      "away_team_name": "Aston Villa",
      "goals_home": 3,
      "goals_away": 2,
      "ht_home": 2,
      "ht_away": 0,
      "status": "FT"
    }
  ]
}