[{"teamId":48,"teamName":"West Ham","formation":"4-2-3-1","players":[{"id":253,"name":"A. Areola","number":23,"pos":"G","type":"start"},{"id":171,"name":"K. Walker-Peters","number":2,"pos":"D","type":"start"},{"id":138,"name":"J. Todibo","number":25,"pos":"D","type":"start"},{"id":18744,"name":"M. Kilman","number":3,"pos":"D","type":"start"},{"id":327730,"name":"O. Scarles","number":30,"pos":"D","type":"start"},{"id":326176,"name":"S. Magassa","number":27,"pos":"M","type":"start"},{"id":284446,"name":"F. Potts","number":32,"pos":"M","type":"start"},{"id":19428,"name":"J. Bowen","number":20,"pos":"M","type":"start"},{"id":336585,"name":"M. Fernandes","number":18,"pos":"M","type":"start"},{"id":1646,"name":"Lucas Paqueta","number":10,"pos":"M","type":"start"},{"id":2939,"name":"C. Wilson","number":9,"pos":"F","type":"start"},{"id":15870,"name":"M. Hermansen","number":1,"pos":"G","type":"sub"},{"id":37724,"name":"C. Summerville","number":7,"pos":"F","type":"sub"},{"id":1445,"name":"K. Mavropanos","number":15,"pos":"D","type":"sub"},{"id":2476,"name":"G. Rodriguez","number":24,"pos":"M","type":"sub"},{"id":1243,"name":"T. Soucek","number":28,"pos":"M","type":"sub"},{"id":291363,"name":"G. Earthy","number":40,"pos":"M","type":"sub"},{"id":401278,"name":"M. Kante","number":55,"pos":"M","type":"sub"},{"id":557541,"name":"A. Golambeckis","number":58,"pos":"D","type":"sub"},{"id":553065,"name":"E. Mayers","number":63,"pos":"D","type":"sub"}]},{"teamId":51,"teamName":"Brighton","formation":"4-2-3-1","players":[{"id":129058,"name":"B. Verbruggen","number":1,"pos":"G","type":"start"},{"id":537,"name":"J. Veltman","number":34,"pos":"D","type":"start"},{"id":38695,"name":"J. P. van Hecke","number":6,"pos":"D","type":"start"},{"id":18963,"name":"L. Dunk","number":5,"pos":"D","type":"start"},{"id":1361,"name":"F. Kadioglu","number":24,"pos":"D","type":"start"},{"id":265820,"name":"Y. Ayari","number":26,"pos":"M","type":"start"},{"id":296,"name":"J. Milner","number":20,"pos":"M","type":"start"},{"id":383685,"name":"Y. Minteh","number":11,"pos":"M","type":"start"},{"id":278370,"name":"D. Gomez","number":25,"pos":"M","type":"start"},{"id":162007,"name":"M. De Cuyper","number":29,"pos":"M","type":"start"},{"id":1469,"name":"D. Welbeck","number":18,"pos":"F","type":"start"},{"id":18960,"name":"J. Steele","number":23,"pos":"G","type":"sub"},{"id":328225,"name":"B. Gruda","number":8,"pos":"M","type":"sub"},{"id":90590,"name":"G. Rutter","number":10,"pos":"F","type":"sub"},{"id":305730,"name":"J. Hinshelwood","number":13,"pos":"M","type":"sub"},{"id":329369,"name":"T. Watson","number":14,"pos":"F","type":"sub"},{"id":392482,"name":"C. Kostoulas","number":19,"pos":"F","type":"sub"},{"id":22160,"name":"O. Boscagli","number":21,"pos":"D","type":"sub"},{"id":106835,"name":"K. Mitoma","number":22,"pos":"M","type":"sub"},{"id":342063,"name":"D. Coppola","number":42,"pos":"D","type":"sub"}]}]